{
    "status": "1",
    "msg": "提示消息",
    "data": [
        {
            "name": "今日新增量",
            "num": "13,256",
            "round_ratio": "+15.1%"
        },
        {
            "name": "今日优质数",
            "num": "3,256",
            "round_ratio": "+15.1%"
        },
        {
            "name": "今日优质率",
            "num": "3,256",
            "round_ratio": "+15.1%"
        },
        {
            "name": "今日约检数",
            "num": "3,256",
            "round_ratio": "-15.1%"
        },
        {
            "name": "今日约检率",
            "num": "3,256",
            "round_ratio": "-15.1%"
        }  
    ]   
}